update_project/__init__.py
update_project/main.py
update_project/update_app.py
update_project/update_pip.py
update_project/utils.py
update_pip_packages-0.1.4.dist-info/METADATA
update_pip_packages-0.1.4.dist-info/WHEEL
update_pip_packages-0.1.4.dist-info/entry_points.txt
update_pip_packages-0.1.4.dist-info/RECORD
