Metadata-Version: 2.1
Name: update-pip-packages
Version: 0.1.4
Summary: 
Author: OleksandrMakarov
Requires-Python: >=3.10,<4.0
Classifier: Programming Language :: Python :: 3
Classifier: Programming Language :: Python :: 3.10
Classifier: Programming Language :: Python :: 3.11
Requires-Dist: distro (>=1.8.0,<2.0.0)
Requires-Dist: toml (>=0.10.2,<0.11.0)
